LICENSE
MANIFEST.in
README.rst
setup.py
DrawTurksHead/__init__.py
DrawTurksHead/__main__.py
DrawTurksHead/_turkshead.cpp
DrawTurksHead/color.py
DrawTurksHead/mosaic.py
DrawTurksHead/tests.py
DrawTurksHead/turkshead.py
DrawTurksHead.egg-info/PKG-INFO
DrawTurksHead.egg-info/SOURCES.txt
DrawTurksHead.egg-info/dependency_links.txt
DrawTurksHead.egg-info/requires.txt
DrawTurksHead.egg-info/top_level.txt
DrawTurksHead/knot/__init__.py
DrawTurksHead/knot/__main__.py
DrawTurksHead/knot/knot.py
DrawTurksHead/knot/tests.py